example_template_service/__init__.py
example_template_service/api_v1/__init__.py
example_template_service/api_v1/example_service.py
example_template_service/app.py
example_template_service/constants.py
example_template_service/metrics.py
example_template_service/run.py
example_template_service/service.py
example_template_service/utils.py
example_template_service/version.py
example_template_service-1.0.0.dist-info/entry_points.txt
example_template_service-1.0.0.dist-info/LICENSE.txt
example_template_service-1.0.0.dist-info/WHEEL
example_template_service-1.0.0.dist-info/METADATA
example_template_service-1.0.0.dist-info/RECORD
